imbd_quotes/__init__.py
imbd_quotes/quotes.py
imbd_quotes/utils.py
imbd_quotes-0.1.1.dist-info/METADATA
imbd_quotes-0.1.1.dist-info/RECORD
imbd_quotes-0.1.1.dist-info/WHEEL
imbd_quotes-0.1.1.dist-info/top_level.txt
